logging_prefixes/__init__.py
logging_prefixes/adapter.py
logging_prefixes/coerce.py
logging_prefixes/funcwrap.py
logging_prefixes-0.2.2.dist-info/METADATA
logging_prefixes-0.2.2.dist-info/RECORD
logging_prefixes-0.2.2.dist-info/WHEEL
logging_prefixes-0.2.2.dist-info/top_level.txt
