Metadata-Version: 2.1
Name: logging-prefixes
Version: 0.2.2
Summary: UNKNOWN
Home-page: UNKNOWN
Author: UNKNOWN
Author-email: UNKNOWN
License: UNKNOWN
Platform: UNKNOWN
Requires-Dist: attrs
